emote/__init__.py
emote/callback.py
emote/callbacks.py
emote/env/__init__.py
emote/env/box2d/__init__.py
emote/env/wrappers.py
emote/extra/crud_storage.py
emote/extra/onnx_exporter.py
emote/extra/system_logger.py
emote/memory/README.md
emote/memory/__init__.py
emote/memory/adaptors.py
emote/memory/builder.py
emote/memory/callbacks.py
emote/memory/column.py
emote/memory/core_types.py
emote/memory/fifo_strategy.py
emote/memory/loading.py
emote/memory/memory.py
emote/memory/segment_tree.py
emote/memory/storage.py
emote/memory/strategy.py
emote/memory/table.py
emote/memory/uniform_strategy.py
emote/nn/__init__.py
emote/nn/action_value_mlp.py
emote/nn/curl.py
emote/nn/gaussian_policy.py
emote/nn/initialization.py
emote/nn/layers.py
emote/proxies.py
emote/sac.py
emote/trainer.py
emote/typing.py
emote/utils/__init__.py
emote/utils/gamma_matrix.py
emote/utils/signal.py
emote/utils/spaces.py
emote/utils/threading.py
emote/utils/timed_call.py
emote/utils/weak_reference.py
emote_rl-23.0.0.dist-info/WHEEL
emote_rl-23.0.0.dist-info/METADATA
emote_rl-23.0.0.dist-info/licenses/LICENSE-APACHE
emote_rl-23.0.0.dist-info/licenses/LICENSE-MIT
emote_rl-23.0.0.dist-info/RECORD
