Metadata-Version: 2.1
Name: emote-rl
Version: 23.0.0
Summary: A modular reinforcement learning library
License: MIT
Author-email: Embark Studios <python@embark-studios.com>
Requires-Python: >=3.9
Requires-Dist: onnx>=1.10
Requires-Dist: psutil>=5.8.0
Requires-Dist: setuptools==59.5
Requires-Dist: tensorboard>=2.8.0
Provides-Extra: atari
Requires-Dist: gym[atari,classic_control]~=0.23.0; extra == "atari"
Requires-Dist: box2d-py==2.3.5; extra == "atari"
Requires-Dist: pygame~=2.1.0; extra == "atari"
Provides-Extra: ci
Requires-Dist: gsutil>=4.66; extra == "ci"
Requires-Dist: emote-rl[atari]; extra == "ci"
Provides-Extra: torch
Requires-Dist: torch==1.10.2; extra == "torch"
Project-URL: repository, https://github.com/EmbarkStudios/emote
